frontend/build/asset-manifest.json
frontend/build/favicon.ico
frontend/build/index.html
frontend/build/logo192.png
frontend/build/logo512.png
frontend/build/manifest.json
frontend/build/robots.txt
frontend/build/static/js/main.1f6c940b.js
frontend/build/static/js/main.1f6c940b.js.LICENSE.txt
frontend/build/static/js/main.1f6c940b.js.map
frontend/build/static/js/main.93730130.js
frontend/build/static/js/main.93730130.js.LICENSE.txt
frontend/build/static/js/main.93730130.js.map
frontend/build/static/js/main.a93f4131.js
frontend/build/static/js/main.a93f4131.js.LICENSE.txt
frontend/build/static/js/main.a93f4131.js.map
my_card_component/__init__.py
selector_tarjetas/__init__.py
SelectorTarjetas-0.1.4.dist-info/METADATA
SelectorTarjetas-0.1.4.dist-info/WHEEL
SelectorTarjetas-0.1.4.dist-info/top_level.txt
SelectorTarjetas-0.1.4.dist-info/RECORD
