Metadata-Version: 2.2
Name: SelectorTarjetas
Version: 0.1.4
Summary: Componente de Streamlit para mostrar tarjetas interactivas seleccionables.
Author: Wilfrido CO
Classifier: Programming Language :: Python :: 3
Classifier: License :: OSI Approved :: MIT License
Classifier: Operating System :: OS Independent
Requires-Python: >=3.11
Requires-Dist: streamlit
Dynamic: author
Dynamic: classifier
Dynamic: requires-dist
Dynamic: requires-python
Dynamic: summary
